pychee/__init__.py
pychee/pychee.py
pychee/test.py
pychee-0.2.2.dist-info/LICENSE
pychee-0.2.2.dist-info/METADATA
pychee-0.2.2.dist-info/WHEEL
pychee-0.2.2.dist-info/top_level.txt
pychee-0.2.2.dist-info/RECORD
