Metadata-Version: 2.1
Name: pychee
Version: 0.2.2
Summary: Client for Lychee, written in Python.
Maintainer-email: Quentin Duchemin <quentinduchemin@tuta.io>
License: GNU AFFERO GENERAL PUBLIC LICENSE
Project-URL: Home, https://github.com/Chostakovitch/pychee
Project-URL: Repository, https://github.com/Chostakovitch/pychee
Project-URL: Issues, https://github.com/Chostakovitch/pychee/issues
Project-URL: Documentation, https://chostakovitch.github.io/pychee/index.html
Classifier: Programming Language :: Python :: 3
Classifier: License :: OSI Approved :: GNU Affero General Public License v3
Classifier: Operating System :: OS Independent
Classifier: Topic :: Internet :: WWW/HTTP :: Dynamic Content :: CGI Tools/Libraries
Requires-Python: >=3.7
License-File: LICENSE
Requires-Dist: requests
Provides-Extra: dependencies
Requires-Dist: requests ; extra == 'dependencies'
Provides-Extra: dev
Requires-Dist: pydocstyle ; extra == 'dev'
Requires-Dist: pylint ; extra == 'dev'
Provides-Extra: test
Requires-Dist: pytest ; extra == 'test'
